lutar/__init__.py
lutar/commons/__init__.py
lutar/commons/helpers.py
lutar/commons/parallel.py
lutar/techtable/__init__.py
lutar/techtable/tt.py
lutar/techtable/funcs/__init__.py
lutar/techtable/funcs/overlap.py
lutar-0.1.dist-info/LICENSE.txt
lutar-0.1.dist-info/METADATA
lutar-0.1.dist-info/WHEEL
lutar-0.1.dist-info/top_level.txt
lutar-0.1.dist-info/RECORD
