Metadata-Version: 2.1
Name: lutar
Version: 0.1
Summary: Lu's Useful Technical Analysis Repository
Home-page: https://github.com/zhiyilv/lutar
Author: Zhiyi Lu
Author-email: zhiyilv@outlook.com
License: UNKNOWN
Platform: UNKNOWN
Requires-Python: >=3.6.0
Requires-Dist: pandas
Requires-Dist: joblib
